blink/__init__.py
blink/utils.py
blink_config-0.0.4.dist-info/LICENSE
blink_config-0.0.4.dist-info/METADATA
blink_config-0.0.4.dist-info/WHEEL
blink_config-0.0.4.dist-info/top_level.txt
blink_config-0.0.4.dist-info/RECORD
