Metadata-Version: 2.1
Name: blink-config
Version: 0.0.4
Summary: A hot-reload configuration dictionary
Home-page: https://github.com/legendof-selda/blink
Provides-Extra: ini
Requires-Dist: configparser ; extra == 'ini'
Provides-Extra: toml
Requires-Dist: toml ; extra == 'toml'
Provides-Extra: xml
Requires-Dist: xmltodict (==0.12.0) ; extra == 'xml'
Provides-Extra: yaml
Requires-Dist: PyYAML ; extra == 'yaml'
